qa_pytest_commons/__init__.py
qa_pytest_commons/abstract_tests_base.py
qa_pytest_commons/base_configuration.py
qa_pytest_commons/bdd_keywords.py
qa_pytest_commons/generic_steps.py
qa_pytest_commons-0.1.1.dist-info/METADATA
qa_pytest_commons-0.1.1.dist-info/WHEEL
qa_pytest_commons-0.1.1.dist-info/RECORD
